{"@t":"2024-12-10T07:03:38.2154596Z","@mt":"{StartMessage} [Timing {TimingId}]","StartMessage":"Booting Umbraco 8.18.14.","TimingId":"7a682b2","SourceContext":"Umbraco.Core.Runtime.CoreRuntime","ProcessId":12688,"ProcessName":"iisexpress","ThreadId":1,"AppDomainId":2,"AppDomainAppId":"LMW3SVC2ROOT","MachineName":"LAPTOP-FTNNAFT4","Log4NetLevel":"INFO ","HttpRequestNumber":1,"HttpRequestId":"330912db-30a0-4f48-9b32-18ebb0b076b9"}
{"@t":"2024-12-10T07:03:38.2471420Z","@mt":"Booting site '{HostingSiteName}', app '{HostingApplicationID}', path '{HostingPhysicalPath}', server '{MachineName}'.","HostingSiteName":"nicecyprj","HostingApplicationID":"/LM/W3SVC/2/ROOT","HostingPhysicalPath":"D:\\AppUser\\SaveCode\\Umbraco\\dustin-nicecy\\nicecyprj\\nicecyprj\\","MachineName":"LAPTOP-FTNNAFT4","SourceContext":"Umbraco.Core.Runtime.CoreRuntime","ProcessId":12688,"ProcessName":"iisexpress","ThreadId":1,"AppDomainId":2,"AppDomainAppId":"LMW3SVC2ROOT","Log4NetLevel":"INFO ","HttpRequestNumber":1,"HttpRequestId":"330912db-30a0-4f48-9b32-18ebb0b076b9"}
{"@t":"2024-12-10T07:03:38.4284834Z","@mt":"Acquiring.","SourceContext":"Umbraco.Core.Runtime.MainDom","ProcessId":12688,"ProcessName":"iisexpress","ThreadId":1,"AppDomainId":2,"AppDomainAppId":"LMW3SVC2ROOT","MachineName":"LAPTOP-FTNNAFT4","Log4NetLevel":"INFO ","HttpRequestNumber":1,"HttpRequestId":"330912db-30a0-4f48-9b32-18ebb0b076b9"}
{"@t":"2024-12-10T07:03:38.4284834Z","@mt":"Acquired.","SourceContext":"Umbraco.Core.Runtime.MainDom","ProcessId":12688,"ProcessName":"iisexpress","ThreadId":1,"AppDomainId":2,"AppDomainAppId":"LMW3SVC2ROOT","MachineName":"LAPTOP-FTNNAFT4","Log4NetLevel":"INFO ","HttpRequestNumber":1,"HttpRequestId":"330912db-30a0-4f48-9b32-18ebb0b076b9"}
{"@t":"2024-12-10T07:03:40.5852349Z","@mt":"{StartMessage} [Timing {TimingId}]","StartMessage":"Resolving composer types.","TimingId":"f1c5e95","SourceContext":"Umbraco.Core.Runtime.CoreRuntime","ProcessId":12688,"ProcessName":"iisexpress","ThreadId":1,"AppDomainId":2,"AppDomainAppId":"LMW3SVC2ROOT","MachineName":"LAPTOP-FTNNAFT4","Log4NetLevel":"INFO ","HttpRequestNumber":1,"HttpRequestId":"330912db-30a0-4f48-9b32-18ebb0b076b9"}
{"@t":"2024-12-10T07:03:40.7735940Z","@mt":"{EndMessage} ({Duration}ms) [Timing {TimingId}]","EndMessage":"Resolved.","Duration":185,"TimingId":"f1c5e95","SourceContext":"Umbraco.Core.Runtime.CoreRuntime","ProcessId":12688,"ProcessName":"iisexpress","ThreadId":1,"AppDomainId":2,"AppDomainAppId":"LMW3SVC2ROOT","MachineName":"LAPTOP-FTNNAFT4","Log4NetLevel":"INFO ","HttpRequestNumber":1,"HttpRequestId":"330912db-30a0-4f48-9b32-18ebb0b076b9"}
{"@t":"2024-12-10T07:03:41.0013797Z","@mt":"ModelsBuilder.Embedded is disabled, the external ModelsBuilder was detected.","SourceContext":"Umbraco.ModelsBuilder.Embedded.Compose.ModelsBuilderComposer","ProcessId":12688,"ProcessName":"iisexpress","ThreadId":1,"AppDomainId":2,"AppDomainAppId":"LMW3SVC2ROOT","MachineName":"LAPTOP-FTNNAFT4","Log4NetLevel":"INFO ","HttpRequestNumber":1,"HttpRequestId":"330912db-30a0-4f48-9b32-18ebb0b076b9"}
{"@t":"2024-12-10T07:03:42.1815071Z","@mt":"Initializing Umbraco internal event handlers for cache refreshing.","SourceContext":"Umbraco.Web.Cache.DistributedCacheBinderComponent","ProcessId":12688,"ProcessName":"iisexpress","ThreadId":1,"AppDomainId":2,"AppDomainAppId":"LMW3SVC2ROOT","MachineName":"LAPTOP-FTNNAFT4","Log4NetLevel":"INFO ","HttpRequestNumber":1,"HttpRequestId":"330912db-30a0-4f48-9b32-18ebb0b076b9"}
{"@t":"2024-12-10T07:03:42.2757015Z","@mt":"Adding examine event handlers for {RegisteredIndexers} index providers.","RegisteredIndexers":3,"SourceContext":"Umbraco.Web.Search.ExamineComponent","ProcessId":12688,"ProcessName":"iisexpress","ThreadId":1,"AppDomainId":2,"AppDomainAppId":"LMW3SVC2ROOT","MachineName":"LAPTOP-FTNNAFT4","Log4NetLevel":"INFO ","HttpRequestNumber":1,"HttpRequestId":"330912db-30a0-4f48-9b32-18ebb0b076b9"}
{"@t":"2024-12-10T07:03:42.3698726Z","@mt":"{EndMessage} ({Duration}ms) [Timing {TimingId}]","EndMessage":"Booted.","Duration":4166,"TimingId":"7a682b2","SourceContext":"Umbraco.Core.Runtime.CoreRuntime","ProcessId":12688,"ProcessName":"iisexpress","ThreadId":1,"AppDomainId":2,"AppDomainAppId":"LMW3SVC2ROOT","MachineName":"LAPTOP-FTNNAFT4","Log4NetLevel":"INFO ","HttpRequestNumber":1,"HttpRequestId":"330912db-30a0-4f48-9b32-18ebb0b076b9"}
{"@t":"2024-12-10T07:03:42.9690787Z","@mt":"New url {Url} detected, re-discovering application url.","Url":"http://localhost/umbraco","SourceContext":"Umbraco.Core.Sync.ApplicationUrlHelper","ProcessId":12688,"ProcessName":"iisexpress","ThreadId":5,"AppDomainId":2,"AppDomainAppId":"LMW3SVC2ROOT","MachineName":"LAPTOP-FTNNAFT4","Log4NetLevel":"INFO ","HttpRequestNumber":2,"HttpRequestId":"bf8c8be1-dc9e-434b-a19e-a954453b5173"}
{"@t":"2024-12-10T07:03:42.9690787Z","@mt":"ApplicationUrl: {UmbracoAppUrl} (UmbracoModule request)","UmbracoAppUrl":"http://localhost/umbraco","SourceContext":"Umbraco.Core.Sync.ApplicationUrlHelper","ProcessId":12688,"ProcessName":"iisexpress","ThreadId":5,"AppDomainId":2,"AppDomainAppId":"LMW3SVC2ROOT","MachineName":"LAPTOP-FTNNAFT4","Log4NetLevel":"INFO ","HttpRequestNumber":2,"HttpRequestId":"bf8c8be1-dc9e-434b-a19e-a954453b5173"}
{"@t":"2024-12-10T07:03:44.4712145Z","@mt":"Registered with MainDom, localContentDbExists? {LocalContentDbExists}, localMediaDbExists? {LocalMediaDbExists}","LocalContentDbExists":true,"LocalMediaDbExists":true,"SourceContext":"Umbraco.Web.PublishedCache.NuCache.PublishedSnapshotService","ProcessId":12688,"ProcessName":"iisexpress","ThreadId":6,"AppDomainId":2,"AppDomainAppId":"LMW3SVC2ROOT","MachineName":"LAPTOP-FTNNAFT4","Log4NetLevel":"INFO ","HttpRequestNumber":3,"HttpRequestId":"3ebefade-0c9a-4526-af6b-a91433071e2a"}
{"@t":"2024-12-10T07:03:44.4712145Z","@mt":"Creating the content store, localContentDbExists? {LocalContentDbExists}","LocalContentDbExists":true,"SourceContext":"Umbraco.Web.PublishedCache.NuCache.PublishedSnapshotService","ProcessId":12688,"ProcessName":"iisexpress","ThreadId":6,"AppDomainId":2,"AppDomainAppId":"LMW3SVC2ROOT","MachineName":"LAPTOP-FTNNAFT4","Log4NetLevel":"INFO ","HttpRequestNumber":3,"HttpRequestId":"3ebefade-0c9a-4526-af6b-a91433071e2a"}
{"@t":"2024-12-10T07:03:44.4712145Z","@mt":"Creating the media store, localMediaDbExists? {LocalMediaDbExists}","LocalMediaDbExists":true,"SourceContext":"Umbraco.Web.PublishedCache.NuCache.PublishedSnapshotService","ProcessId":12688,"ProcessName":"iisexpress","ThreadId":6,"AppDomainId":2,"AppDomainAppId":"LMW3SVC2ROOT","MachineName":"LAPTOP-FTNNAFT4","Log4NetLevel":"INFO ","HttpRequestNumber":3,"HttpRequestId":"3ebefade-0c9a-4526-af6b-a91433071e2a"}
{"@t":"2024-12-10T07:03:44.5649535Z","@mt":"No last synced Id found, this generally means this is a new server/install. The server will build its caches and indexes, and then adjust its last synced Id to the latest found in the database and maintain cache updates based on that Id.","@l":"Warning","SourceContext":"Umbraco.Core.Sync.DatabaseServerMessenger","ProcessId":12688,"ProcessName":"iisexpress","ThreadId":6,"AppDomainId":2,"AppDomainAppId":"LMW3SVC2ROOT","MachineName":"LAPTOP-FTNNAFT4","Log4NetLevel":"WARN ","HttpRequestNumber":3,"HttpRequestId":"3ebefade-0c9a-4526-af6b-a91433071e2a"}
{"@t":"2024-12-10T07:03:45.4774143Z","@mt":"{StartMessage} [Timing {TimingId}]","StartMessage":"Loading content from database","TimingId":"028c4e5","SourceContext":"Umbraco.Web.PublishedCache.NuCache.PublishedSnapshotService","ProcessId":12688,"ProcessName":"iisexpress","ThreadId":6,"AppDomainId":2,"AppDomainAppId":"LMW3SVC2ROOT","MachineName":"LAPTOP-FTNNAFT4","Log4NetLevel":"INFO ","HttpRequestNumber":3,"HttpRequestId":"3ebefade-0c9a-4526-af6b-a91433071e2a"}
{"@t":"2024-12-10T07:03:45.8328130Z","@mt":"{EndMessage} ({Duration}ms) [Timing {TimingId}]","EndMessage":"Completed.","Duration":361,"TimingId":"028c4e5","SourceContext":"Umbraco.Web.PublishedCache.NuCache.PublishedSnapshotService","ProcessId":12688,"ProcessName":"iisexpress","ThreadId":6,"AppDomainId":2,"AppDomainAppId":"LMW3SVC2ROOT","MachineName":"LAPTOP-FTNNAFT4","Log4NetLevel":"INFO ","HttpRequestNumber":3,"HttpRequestId":"3ebefade-0c9a-4526-af6b-a91433071e2a"}
{"@t":"2024-12-10T07:03:45.8728109Z","@mt":"{StartMessage} [Timing {TimingId}]","StartMessage":"Loading media from database","TimingId":"5848407","SourceContext":"Umbraco.Web.PublishedCache.NuCache.PublishedSnapshotService","ProcessId":12688,"ProcessName":"iisexpress","ThreadId":6,"AppDomainId":2,"AppDomainAppId":"LMW3SVC2ROOT","MachineName":"LAPTOP-FTNNAFT4","Log4NetLevel":"INFO ","HttpRequestNumber":3,"HttpRequestId":"3ebefade-0c9a-4526-af6b-a91433071e2a"}
{"@t":"2024-12-10T07:03:45.9821985Z","@mt":"{EndMessage} ({Duration}ms) [Timing {TimingId}]","EndMessage":"Completed.","Duration":95,"TimingId":"5848407","SourceContext":"Umbraco.Web.PublishedCache.NuCache.PublishedSnapshotService","ProcessId":12688,"ProcessName":"iisexpress","ThreadId":6,"AppDomainId":2,"AppDomainAppId":"LMW3SVC2ROOT","MachineName":"LAPTOP-FTNNAFT4","Log4NetLevel":"INFO ","HttpRequestNumber":3,"HttpRequestId":"3ebefade-0c9a-4526-af6b-a91433071e2a"}
{"@t":"2024-12-10T07:03:46.1071959Z","@mt":"Starting initialize async background thread.","SourceContext":"Umbraco.Web.Search.BackgroundIndexRebuilder","ProcessId":12688,"ProcessName":"iisexpress","ThreadId":6,"AppDomainId":2,"AppDomainAppId":"LMW3SVC2ROOT","MachineName":"LAPTOP-FTNNAFT4","Log4NetLevel":"INFO ","HttpRequestNumber":3,"HttpRequestId":"3ebefade-0c9a-4526-af6b-a91433071e2a"}
{"@t":"2024-12-10T07:05:05.8423269Z","@mt":"[{EventType}] Event Id: {EventId}, State: {State}","EventType":"Information","EventId":0,"State":"Login attempt succeeded for username clark@gmail.com from IP address ::1","SourceContext":"Umbraco.Core.Logging.OwinLogger","ProcessId":12688,"ProcessName":"iisexpress","ThreadId":11,"AppDomainId":2,"AppDomainAppId":"LMW3SVC2ROOT","MachineName":"LAPTOP-FTNNAFT4","Log4NetLevel":"INFO ","HttpRequestNumber":4,"HttpRequestId":"153c0fe9-d18d-4eac-b3c5-7d332da48b53"}
{"@t":"2024-12-10T07:05:05.8423269Z","@mt":"[{EventType}] Event Id: {EventId}, State: {State}","EventType":"Information","EventId":0,"State":"User: clark@gmail.com logged in from IP address ::1","SourceContext":"Umbraco.Core.Logging.OwinLogger","ProcessId":12688,"ProcessName":"iisexpress","ThreadId":11,"AppDomainId":2,"AppDomainAppId":"LMW3SVC2ROOT","MachineName":"LAPTOP-FTNNAFT4","Log4NetLevel":"INFO ","HttpRequestNumber":4,"HttpRequestId":"153c0fe9-d18d-4eac-b3c5-7d332da48b53"}
{"@t":"2024-12-10T07:06:51.1984265Z","@mt":"Scheduled health check results:","SourceContext":"Umbraco.Web.HealthCheck.HealthCheckResults","ProcessId":12688,"ProcessName":"iisexpress","ThreadId":18,"AppDomainId":2,"AppDomainAppId":"LMW3SVC2ROOT","MachineName":"LAPTOP-FTNNAFT4","Log4NetLevel":"INFO "}
{"@t":"2024-12-10T07:06:51.1998653Z","@mt":"Checks for '{HealthCheckName}' all completed successfully.","HealthCheckName":"Folder & File Permissions","SourceContext":"Umbraco.Web.HealthCheck.HealthCheckResults","ProcessId":12688,"ProcessName":"iisexpress","ThreadId":18,"AppDomainId":2,"AppDomainAppId":"LMW3SVC2ROOT","MachineName":"LAPTOP-FTNNAFT4","Log4NetLevel":"INFO "}
{"@t":"2024-12-10T07:06:51.2007681Z","@mt":"Result for {HealthCheckName}: {HealthCheckResult}, Message: '{HealthCheckMessage}'","HealthCheckName":"Folder & File Permissions","HealthCheckResult":"Success","HealthCheckMessage":"All folders have the correct permissions set.","SourceContext":"Umbraco.Web.HealthCheck.HealthCheckResults","ProcessId":12688,"ProcessName":"iisexpress","ThreadId":18,"AppDomainId":2,"AppDomainAppId":"LMW3SVC2ROOT","MachineName":"LAPTOP-FTNNAFT4","Log4NetLevel":"INFO "}
{"@t":"2024-12-10T07:06:51.2014916Z","@mt":"Result for {HealthCheckName}: {HealthCheckResult}, Message: '{HealthCheckMessage}'","HealthCheckName":"Folder & File Permissions","HealthCheckResult":"Success","HealthCheckMessage":"All files have the correct permissions set.","SourceContext":"Umbraco.Web.HealthCheck.HealthCheckResults","ProcessId":12688,"ProcessName":"iisexpress","ThreadId":18,"AppDomainId":2,"AppDomainAppId":"LMW3SVC2ROOT","MachineName":"LAPTOP-FTNNAFT4","Log4NetLevel":"INFO "}
{"@t":"2024-12-10T07:06:51.2028797Z","@mt":"Checks for '{HealthCheckName}' completed with errors.","@l":"Warning","HealthCheckName":"SMTP Settings","SourceContext":"Umbraco.Web.HealthCheck.HealthCheckResults","ProcessId":12688,"ProcessName":"iisexpress","ThreadId":18,"AppDomainId":2,"AppDomainAppId":"LMW3SVC2ROOT","MachineName":"LAPTOP-FTNNAFT4","Log4NetLevel":"WARN "}
{"@t":"2024-12-10T07:06:51.2028797Z","@mt":"Result for {HealthCheckName}: {HealthCheckResult}, Message: '{HealthCheckMessage}'","HealthCheckName":"SMTP Settings","HealthCheckResult":"Error","HealthCheckMessage":"In the Web.config file system.net/mailsettings section, the host is not configured.","SourceContext":"Umbraco.Web.HealthCheck.HealthCheckResults","ProcessId":12688,"ProcessName":"iisexpress","ThreadId":18,"AppDomainId":2,"AppDomainAppId":"LMW3SVC2ROOT","MachineName":"LAPTOP-FTNNAFT4","Log4NetLevel":"INFO "}
{"@t":"2024-12-10T07:06:51.2028797Z","@mt":"Checks for '{HealthCheckName}' completed with errors.","@l":"Warning","HealthCheckName":"Application URL Configuration","SourceContext":"Umbraco.Web.HealthCheck.HealthCheckResults","ProcessId":12688,"ProcessName":"iisexpress","ThreadId":18,"AppDomainId":2,"AppDomainAppId":"LMW3SVC2ROOT","MachineName":"LAPTOP-FTNNAFT4","Log4NetLevel":"WARN "}
{"@t":"2024-12-10T07:06:51.2028797Z","@mt":"Result for {HealthCheckName}: {HealthCheckResult}, Message: '{HealthCheckMessage}'","HealthCheckName":"Application URL Configuration","HealthCheckResult":"Warning","HealthCheckMessage":"The 'umbracoApplicationUrl' option is not set in your umbracoSettings.config file.","SourceContext":"Umbraco.Web.HealthCheck.HealthCheckResults","ProcessId":12688,"ProcessName":"iisexpress","ThreadId":18,"AppDomainId":2,"AppDomainAppId":"LMW3SVC2ROOT","MachineName":"LAPTOP-FTNNAFT4","Log4NetLevel":"INFO "}
{"@t":"2024-12-10T07:06:51.2028797Z","@mt":"Checks for '{HealthCheckName}' completed with errors.","@l":"Warning","HealthCheckName":"Cross-site scripting Protection (X-XSS-Protection header)","SourceContext":"Umbraco.Web.HealthCheck.HealthCheckResults","ProcessId":12688,"ProcessName":"iisexpress","ThreadId":18,"AppDomainId":2,"AppDomainAppId":"LMW3SVC2ROOT","MachineName":"LAPTOP-FTNNAFT4","Log4NetLevel":"WARN "}
{"@t":"2024-12-10T07:06:51.2028797Z","@mt":"Result for {HealthCheckName}: {HealthCheckResult}, Message: '{HealthCheckMessage}'","HealthCheckName":"Cross-site scripting Protection (X-XSS-Protection header)","HealthCheckResult":"Error","HealthCheckMessage":"The header <strong>X-XSS-Protection</strong> was not found.","SourceContext":"Umbraco.Web.HealthCheck.HealthCheckResults","ProcessId":12688,"ProcessName":"iisexpress","ThreadId":18,"AppDomainId":2,"AppDomainAppId":"LMW3SVC2ROOT","MachineName":"LAPTOP-FTNNAFT4","Log4NetLevel":"INFO "}
{"@t":"2024-12-10T07:06:51.2028797Z","@mt":"Checks for '{HealthCheckName}' completed with errors.","@l":"Warning","HealthCheckName":"Cookie hijacking and protocol downgrade attacks Protection (Strict-Transport-Security Header (HSTS))","SourceContext":"Umbraco.Web.HealthCheck.HealthCheckResults","ProcessId":12688,"ProcessName":"iisexpress","ThreadId":18,"AppDomainId":2,"AppDomainAppId":"LMW3SVC2ROOT","MachineName":"LAPTOP-FTNNAFT4","Log4NetLevel":"WARN "}
{"@t":"2024-12-10T07:06:51.2028797Z","@mt":"Result for {HealthCheckName}: {HealthCheckResult}, Message: '{HealthCheckMessage}'","HealthCheckName":"Cookie hijacking and protocol downgrade attacks Protection (Strict-Transport-Security Header (HSTS))","HealthCheckResult":"Error","HealthCheckMessage":"The header <strong>Strict-Transport-Security</strong> was not found.","SourceContext":"Umbraco.Web.HealthCheck.HealthCheckResults","ProcessId":12688,"ProcessName":"iisexpress","ThreadId":18,"AppDomainId":2,"AppDomainAppId":"LMW3SVC2ROOT","MachineName":"LAPTOP-FTNNAFT4","Log4NetLevel":"INFO "}
{"@t":"2024-12-10T07:06:51.2028797Z","@mt":"Checks for '{HealthCheckName}' completed with errors.","@l":"Warning","HealthCheckName":"Content/MIME Sniffing Protection","SourceContext":"Umbraco.Web.HealthCheck.HealthCheckResults","ProcessId":12688,"ProcessName":"iisexpress","ThreadId":18,"AppDomainId":2,"AppDomainAppId":"LMW3SVC2ROOT","MachineName":"LAPTOP-FTNNAFT4","Log4NetLevel":"WARN "}
{"@t":"2024-12-10T07:06:51.2028797Z","@mt":"Result for {HealthCheckName}: {HealthCheckResult}, Message: '{HealthCheckMessage}'","HealthCheckName":"Content/MIME Sniffing Protection","HealthCheckResult":"Error","HealthCheckMessage":"The header or meta-tag <strong>X-Content-Type-Options</strong> used to protect against MIME sniffing vulnerabilities was not found.","SourceContext":"Umbraco.Web.HealthCheck.HealthCheckResults","ProcessId":12688,"ProcessName":"iisexpress","ThreadId":18,"AppDomainId":2,"AppDomainAppId":"LMW3SVC2ROOT","MachineName":"LAPTOP-FTNNAFT4","Log4NetLevel":"INFO "}
{"@t":"2024-12-10T07:06:51.2028797Z","@mt":"Checks for '{HealthCheckName}' completed with errors.","@l":"Warning","HealthCheckName":"Excessive Headers","SourceContext":"Umbraco.Web.HealthCheck.HealthCheckResults","ProcessId":12688,"ProcessName":"iisexpress","ThreadId":18,"AppDomainId":2,"AppDomainAppId":"LMW3SVC2ROOT","MachineName":"LAPTOP-FTNNAFT4","Log4NetLevel":"WARN "}
{"@t":"2024-12-10T07:06:51.2028797Z","@mt":"Result for {HealthCheckName}: {HealthCheckResult}, Message: '{HealthCheckMessage}'","HealthCheckName":"Excessive Headers","HealthCheckResult":"Warning","HealthCheckMessage":"The following headers revealing information about the website technology were found: <strong>Server, X-Powered-By</strong>.","SourceContext":"Umbraco.Web.HealthCheck.HealthCheckResults","ProcessId":12688,"ProcessName":"iisexpress","ThreadId":18,"AppDomainId":2,"AppDomainAppId":"LMW3SVC2ROOT","MachineName":"LAPTOP-FTNNAFT4","Log4NetLevel":"INFO "}
{"@t":"2024-12-10T07:06:51.2028797Z","@mt":"Checks for '{HealthCheckName}' completed with errors.","@l":"Warning","HealthCheckName":"Click-Jacking Protection","SourceContext":"Umbraco.Web.HealthCheck.HealthCheckResults","ProcessId":12688,"ProcessName":"iisexpress","ThreadId":18,"AppDomainId":2,"AppDomainAppId":"LMW3SVC2ROOT","MachineName":"LAPTOP-FTNNAFT4","Log4NetLevel":"WARN "}
{"@t":"2024-12-10T07:06:51.2028797Z","@mt":"Result for {HealthCheckName}: {HealthCheckResult}, Message: '{HealthCheckMessage}'","HealthCheckName":"Click-Jacking Protection","HealthCheckResult":"Error","HealthCheckMessage":"The header or meta-tag <strong>X-Frame-Options</strong> used to control whether a site can be IFRAMEd by another was not found.","SourceContext":"Umbraco.Web.HealthCheck.HealthCheckResults","ProcessId":12688,"ProcessName":"iisexpress","ThreadId":18,"AppDomainId":2,"AppDomainAppId":"LMW3SVC2ROOT","MachineName":"LAPTOP-FTNNAFT4","Log4NetLevel":"INFO "}
{"@t":"2024-12-10T07:06:51.2028797Z","@mt":"Checks for '{HealthCheckName}' completed with errors.","@l":"Warning","HealthCheckName":"HTTPS Configuration","SourceContext":"Umbraco.Web.HealthCheck.HealthCheckResults","ProcessId":12688,"ProcessName":"iisexpress","ThreadId":18,"AppDomainId":2,"AppDomainAppId":"LMW3SVC2ROOT","MachineName":"LAPTOP-FTNNAFT4","Log4NetLevel":"WARN "}
{"@t":"2024-12-10T07:06:51.2028797Z","@mt":"Result for {HealthCheckName}: {HealthCheckResult}, Message: '{HealthCheckMessage}'","HealthCheckName":"HTTPS Configuration","HealthCheckResult":"Error","HealthCheckMessage":"You are currently not viewing the site using the HTTPS scheme.","SourceContext":"Umbraco.Web.HealthCheck.HealthCheckResults","ProcessId":12688,"ProcessName":"iisexpress","ThreadId":18,"AppDomainId":2,"AppDomainAppId":"LMW3SVC2ROOT","MachineName":"LAPTOP-FTNNAFT4","Log4NetLevel":"INFO "}
{"@t":"2024-12-10T07:06:51.2028797Z","@mt":"Result for {HealthCheckName}: {HealthCheckResult}, Message: '{HealthCheckMessage}'","HealthCheckName":"HTTPS Configuration","HealthCheckResult":"Info","HealthCheckMessage":"The appSetting 'Umbraco.Core.UseHttps' is set to 'false' in your web.config file. Once you access this site using the HTTPS scheme, that should be set to 'true'.","SourceContext":"Umbraco.Web.HealthCheck.HealthCheckResults","ProcessId":12688,"ProcessName":"iisexpress","ThreadId":18,"AppDomainId":2,"AppDomainAppId":"LMW3SVC2ROOT","MachineName":"LAPTOP-FTNNAFT4","Log4NetLevel":"INFO "}
{"@t":"2024-12-10T07:06:51.2028797Z","@mt":"Result for {HealthCheckName}: {HealthCheckResult}, Message: '{HealthCheckMessage}'","HealthCheckName":"HTTPS Configuration","HealthCheckResult":"Error","HealthCheckMessage":"Error pinging the URL https://localhost/umbraco - 'Unable to connect to the remote server'","SourceContext":"Umbraco.Web.HealthCheck.HealthCheckResults","ProcessId":12688,"ProcessName":"iisexpress","ThreadId":18,"AppDomainId":2,"AppDomainAppId":"LMW3SVC2ROOT","MachineName":"LAPTOP-FTNNAFT4","Log4NetLevel":"INFO "}
{"@t":"2024-12-10T07:06:51.2028797Z","@mt":"Checks for '{HealthCheckName}' all completed successfully.","HealthCheckName":"Database data integrity check","SourceContext":"Umbraco.Web.HealthCheck.HealthCheckResults","ProcessId":12688,"ProcessName":"iisexpress","ThreadId":18,"AppDomainId":2,"AppDomainAppId":"LMW3SVC2ROOT","MachineName":"LAPTOP-FTNNAFT4","Log4NetLevel":"INFO "}
{"@t":"2024-12-10T07:06:51.2028797Z","@mt":"Result for {HealthCheckName}: {HealthCheckResult}, Message: '{HealthCheckMessage}'","HealthCheckName":"Database data integrity check","HealthCheckResult":"Success","HealthCheckMessage":"<p>All document paths are valid</p>\r\n","SourceContext":"Umbraco.Web.HealthCheck.HealthCheckResults","ProcessId":12688,"ProcessName":"iisexpress","ThreadId":18,"AppDomainId":2,"AppDomainAppId":"LMW3SVC2ROOT","MachineName":"LAPTOP-FTNNAFT4","Log4NetLevel":"INFO "}
{"@t":"2024-12-10T07:06:51.2028797Z","@mt":"Result for {HealthCheckName}: {HealthCheckResult}, Message: '{HealthCheckMessage}'","HealthCheckName":"Database data integrity check","HealthCheckResult":"Success","HealthCheckMessage":"<p>All media paths are valid</p>\r\n","SourceContext":"Umbraco.Web.HealthCheck.HealthCheckResults","ProcessId":12688,"ProcessName":"iisexpress","ThreadId":18,"AppDomainId":2,"AppDomainAppId":"LMW3SVC2ROOT","MachineName":"LAPTOP-FTNNAFT4","Log4NetLevel":"INFO "}
{"@t":"2024-12-10T07:06:51.2028797Z","@mt":"Checks for '{HealthCheckName}' completed with errors.","@l":"Warning","HealthCheckName":"Macro errors","SourceContext":"Umbraco.Web.HealthCheck.HealthCheckResults","ProcessId":12688,"ProcessName":"iisexpress","ThreadId":18,"AppDomainId":2,"AppDomainAppId":"LMW3SVC2ROOT","MachineName":"LAPTOP-FTNNAFT4","Log4NetLevel":"WARN "}
{"@t":"2024-12-10T07:06:51.2028797Z","@mt":"Result for {HealthCheckName}: {HealthCheckResult}, Message: '{HealthCheckMessage}'","HealthCheckName":"Macro errors","HealthCheckResult":"Error","HealthCheckMessage":"MacroErrors are set to 'throw' which will prevent some or all pages in your site from loading completely if there are any errors in macros. Rectifying this will set the value to 'inline'.","SourceContext":"Umbraco.Web.HealthCheck.HealthCheckResults","ProcessId":12688,"ProcessName":"iisexpress","ThreadId":18,"AppDomainId":2,"AppDomainAppId":"LMW3SVC2ROOT","MachineName":"LAPTOP-FTNNAFT4","Log4NetLevel":"INFO "}
{"@t":"2024-12-10T07:06:51.2028797Z","@mt":"Checks for '{HealthCheckName}' completed with errors.","@l":"Warning","HealthCheckName":"Notification Email Settings","SourceContext":"Umbraco.Web.HealthCheck.HealthCheckResults","ProcessId":12688,"ProcessName":"iisexpress","ThreadId":18,"AppDomainId":2,"AppDomainAppId":"LMW3SVC2ROOT","MachineName":"LAPTOP-FTNNAFT4","Log4NetLevel":"WARN "}
{"@t":"2024-12-10T07:06:51.2028797Z","@mt":"Result for {HealthCheckName}: {HealthCheckResult}, Message: '{HealthCheckMessage}'","HealthCheckName":"Notification Email Settings","HealthCheckResult":"Error","HealthCheckMessage":"Notification email is still set to the default value of <strong>your@email.here</strong>.","SourceContext":"Umbraco.Web.HealthCheck.HealthCheckResults","ProcessId":12688,"ProcessName":"iisexpress","ThreadId":18,"AppDomainId":2,"AppDomainAppId":"LMW3SVC2ROOT","MachineName":"LAPTOP-FTNNAFT4","Log4NetLevel":"INFO "}
{"@t":"2024-12-10T07:06:51.2028797Z","@mt":"Checks for '{HealthCheckName}' all completed successfully.","HealthCheckName":"Try Skip IIS Custom Errors","SourceContext":"Umbraco.Web.HealthCheck.HealthCheckResults","ProcessId":12688,"ProcessName":"iisexpress","ThreadId":18,"AppDomainId":2,"AppDomainAppId":"LMW3SVC2ROOT","MachineName":"LAPTOP-FTNNAFT4","Log4NetLevel":"INFO "}
{"@t":"2024-12-10T07:06:51.2028797Z","@mt":"Result for {HealthCheckName}: {HealthCheckResult}, Message: '{HealthCheckMessage}'","HealthCheckName":"Try Skip IIS Custom Errors","HealthCheckResult":"Success","HealthCheckMessage":"Try Skip IIS Custom Errors is set to 'true' and you're using IIS version '10.0'.","SourceContext":"Umbraco.Web.HealthCheck.HealthCheckResults","ProcessId":12688,"ProcessName":"iisexpress","ThreadId":18,"AppDomainId":2,"AppDomainAppId":"LMW3SVC2ROOT","MachineName":"LAPTOP-FTNNAFT4","Log4NetLevel":"INFO "}
{"@t":"2024-12-10T07:06:51.2028797Z","@mt":"Checks for '{HealthCheckName}' all completed successfully.","HealthCheckName":"Custom Errors","SourceContext":"Umbraco.Web.HealthCheck.HealthCheckResults","ProcessId":12688,"ProcessName":"iisexpress","ThreadId":18,"AppDomainId":2,"AppDomainAppId":"LMW3SVC2ROOT","MachineName":"LAPTOP-FTNNAFT4","Log4NetLevel":"INFO "}
{"@t":"2024-12-10T07:06:51.2028797Z","@mt":"Result for {HealthCheckName}: {HealthCheckResult}, Message: '{HealthCheckMessage}'","HealthCheckName":"Custom Errors","HealthCheckResult":"Success","HealthCheckMessage":"Custom errors are set to 'RemoteOnly'.","SourceContext":"Umbraco.Web.HealthCheck.HealthCheckResults","ProcessId":12688,"ProcessName":"iisexpress","ThreadId":18,"AppDomainId":2,"AppDomainAppId":"LMW3SVC2ROOT","MachineName":"LAPTOP-FTNNAFT4","Log4NetLevel":"INFO "}
{"@t":"2024-12-10T07:06:51.2028797Z","@mt":"Checks for '{HealthCheckName}' all completed successfully.","HealthCheckName":"Trace Mode","SourceContext":"Umbraco.Web.HealthCheck.HealthCheckResults","ProcessId":12688,"ProcessName":"iisexpress","ThreadId":18,"AppDomainId":2,"AppDomainAppId":"LMW3SVC2ROOT","MachineName":"LAPTOP-FTNNAFT4","Log4NetLevel":"INFO "}
{"@t":"2024-12-10T07:06:51.2028797Z","@mt":"Result for {HealthCheckName}: {HealthCheckResult}, Message: '{HealthCheckMessage}'","HealthCheckName":"Trace Mode","HealthCheckResult":"Success","HealthCheckMessage":"Trace mode is disabled.","SourceContext":"Umbraco.Web.HealthCheck.HealthCheckResults","ProcessId":12688,"ProcessName":"iisexpress","ThreadId":18,"AppDomainId":2,"AppDomainAppId":"LMW3SVC2ROOT","MachineName":"LAPTOP-FTNNAFT4","Log4NetLevel":"INFO "}
{"@t":"2024-12-10T07:06:51.2028797Z","@mt":"Checks for '{HealthCheckName}' completed with errors.","@l":"Warning","HealthCheckName":"Debug Compilation Mode","SourceContext":"Umbraco.Web.HealthCheck.HealthCheckResults","ProcessId":12688,"ProcessName":"iisexpress","ThreadId":18,"AppDomainId":2,"AppDomainAppId":"LMW3SVC2ROOT","MachineName":"LAPTOP-FTNNAFT4","Log4NetLevel":"WARN "}
{"@t":"2024-12-10T07:06:51.2028797Z","@mt":"Result for {HealthCheckName}: {HealthCheckResult}, Message: '{HealthCheckMessage}'","HealthCheckName":"Debug Compilation Mode","HealthCheckResult":"Error","HealthCheckMessage":"Debug compilation mode is currently enabled. It is recommended to disable this setting before go live.","SourceContext":"Umbraco.Web.HealthCheck.HealthCheckResults","ProcessId":12688,"ProcessName":"iisexpress","ThreadId":18,"AppDomainId":2,"AppDomainAppId":"LMW3SVC2ROOT","MachineName":"LAPTOP-FTNNAFT4","Log4NetLevel":"INFO "}
{"@t":"2024-12-10T07:25:03.6704567Z","@mt":"[{EventType}] Event Id: {EventId}, State: {State}","EventType":"Information","EventId":0,"State":"User logged will be logged out due to timeout: clark@gmail.com, IP Address: ::1","SourceContext":"Umbraco.Core.Logging.OwinLogger","ProcessId":12688,"ProcessName":"iisexpress","ThreadId":160,"AppDomainId":2,"AppDomainAppId":"LMW3SVC2ROOT","MachineName":"LAPTOP-FTNNAFT4","Log4NetLevel":"INFO ","HttpRequestNumber":5,"HttpRequestId":"c2beef5d-41ca-418e-abf8-66546b0d9b7a"}
{"@t":"2024-12-10T10:05:41.8831648Z","@mt":"{StartMessage} [Timing {TimingId}]","StartMessage":"Booting Umbraco 8.18.14.","TimingId":"b91345e","SourceContext":"Umbraco.Core.Runtime.CoreRuntime","ProcessId":24520,"ProcessName":"iisexpress","ThreadId":1,"AppDomainId":2,"AppDomainAppId":"LMW3SVC2ROOT","MachineName":"LAPTOP-FTNNAFT4","Log4NetLevel":"INFO ","HttpRequestNumber":1,"HttpRequestId":"235446dc-d56e-47fa-8d19-544acf859e47"}
{"@t":"2024-12-10T10:05:41.9542932Z","@mt":"Booting site '{HostingSiteName}', app '{HostingApplicationID}', path '{HostingPhysicalPath}', server '{MachineName}'.","HostingSiteName":"nicecyprj","HostingApplicationID":"/LM/W3SVC/2/ROOT","HostingPhysicalPath":"D:\\AppUser\\SaveCode\\Umbraco\\dustin-nicecy\\nicecyprj\\nicecyprj\\","MachineName":"LAPTOP-FTNNAFT4","SourceContext":"Umbraco.Core.Runtime.CoreRuntime","ProcessId":24520,"ProcessName":"iisexpress","ThreadId":1,"AppDomainId":2,"AppDomainAppId":"LMW3SVC2ROOT","Log4NetLevel":"INFO ","HttpRequestNumber":1,"HttpRequestId":"235446dc-d56e-47fa-8d19-544acf859e47"}
{"@t":"2024-12-10T10:05:42.4507194Z","@mt":"Acquiring.","SourceContext":"Umbraco.Core.Runtime.MainDom","ProcessId":24520,"ProcessName":"iisexpress","ThreadId":1,"AppDomainId":2,"AppDomainAppId":"LMW3SVC2ROOT","MachineName":"LAPTOP-FTNNAFT4","Log4NetLevel":"INFO ","HttpRequestNumber":1,"HttpRequestId":"235446dc-d56e-47fa-8d19-544acf859e47"}
{"@t":"2024-12-10T10:05:42.4507194Z","@mt":"Acquired.","SourceContext":"Umbraco.Core.Runtime.MainDom","ProcessId":24520,"ProcessName":"iisexpress","ThreadId":1,"AppDomainId":2,"AppDomainAppId":"LMW3SVC2ROOT","MachineName":"LAPTOP-FTNNAFT4","Log4NetLevel":"INFO ","HttpRequestNumber":1,"HttpRequestId":"235446dc-d56e-47fa-8d19-544acf859e47"}
{"@t":"2024-12-10T10:05:47.6472119Z","@mt":"{StartMessage} [Timing {TimingId}]","StartMessage":"Resolving composer types.","TimingId":"b6038b8","SourceContext":"Umbraco.Core.Runtime.CoreRuntime","ProcessId":24520,"ProcessName":"iisexpress","ThreadId":1,"AppDomainId":2,"AppDomainAppId":"LMW3SVC2ROOT","MachineName":"LAPTOP-FTNNAFT4","Log4NetLevel":"INFO ","HttpRequestNumber":1,"HttpRequestId":"235446dc-d56e-47fa-8d19-544acf859e47"}
{"@t":"2024-12-10T10:05:47.9353248Z","@mt":"{EndMessage} ({Duration}ms) [Timing {TimingId}]","EndMessage":"Resolved.","Duration":287,"TimingId":"b6038b8","SourceContext":"Umbraco.Core.Runtime.CoreRuntime","ProcessId":24520,"ProcessName":"iisexpress","ThreadId":1,"AppDomainId":2,"AppDomainAppId":"LMW3SVC2ROOT","MachineName":"LAPTOP-FTNNAFT4","Log4NetLevel":"INFO ","HttpRequestNumber":1,"HttpRequestId":"235446dc-d56e-47fa-8d19-544acf859e47"}
{"@t":"2024-12-10T10:05:48.4439844Z","@mt":"ModelsBuilder.Embedded is disabled, the external ModelsBuilder was detected.","SourceContext":"Umbraco.ModelsBuilder.Embedded.Compose.ModelsBuilderComposer","ProcessId":24520,"ProcessName":"iisexpress","ThreadId":1,"AppDomainId":2,"AppDomainAppId":"LMW3SVC2ROOT","MachineName":"LAPTOP-FTNNAFT4","Log4NetLevel":"INFO ","HttpRequestNumber":1,"HttpRequestId":"235446dc-d56e-47fa-8d19-544acf859e47"}
{"@t":"2024-12-10T10:05:50.2428164Z","@mt":"Initializing Umbraco internal event handlers for cache refreshing.","SourceContext":"Umbraco.Web.Cache.DistributedCacheBinderComponent","ProcessId":24520,"ProcessName":"iisexpress","ThreadId":1,"AppDomainId":2,"AppDomainAppId":"LMW3SVC2ROOT","MachineName":"LAPTOP-FTNNAFT4","Log4NetLevel":"INFO ","HttpRequestNumber":1,"HttpRequestId":"235446dc-d56e-47fa-8d19-544acf859e47"}
{"@t":"2024-12-10T10:05:50.4354348Z","@mt":"Adding examine event handlers for {RegisteredIndexers} index providers.","RegisteredIndexers":3,"SourceContext":"Umbraco.Web.Search.ExamineComponent","ProcessId":24520,"ProcessName":"iisexpress","ThreadId":1,"AppDomainId":2,"AppDomainAppId":"LMW3SVC2ROOT","MachineName":"LAPTOP-FTNNAFT4","Log4NetLevel":"INFO ","HttpRequestNumber":1,"HttpRequestId":"235446dc-d56e-47fa-8d19-544acf859e47"}
{"@t":"2024-12-10T10:05:50.6455616Z","@mt":"{EndMessage} ({Duration}ms) [Timing {TimingId}]","EndMessage":"Booted.","Duration":8790,"TimingId":"b91345e","SourceContext":"Umbraco.Core.Runtime.CoreRuntime","ProcessId":24520,"ProcessName":"iisexpress","ThreadId":1,"AppDomainId":2,"AppDomainAppId":"LMW3SVC2ROOT","MachineName":"LAPTOP-FTNNAFT4","Log4NetLevel":"INFO ","HttpRequestNumber":1,"HttpRequestId":"235446dc-d56e-47fa-8d19-544acf859e47"}
{"@t":"2024-12-10T10:05:51.5470092Z","@mt":"New url {Url} detected, re-discovering application url.","Url":"http://localhost/umbraco","SourceContext":"Umbraco.Core.Sync.ApplicationUrlHelper","ProcessId":24520,"ProcessName":"iisexpress","ThreadId":7,"AppDomainId":2,"AppDomainAppId":"LMW3SVC2ROOT","MachineName":"LAPTOP-FTNNAFT4","Log4NetLevel":"INFO ","HttpRequestNumber":2,"HttpRequestId":"a760773c-5489-44c7-b49d-a2ac9fada368"}
{"@t":"2024-12-10T10:05:51.5470092Z","@mt":"New url {Url} detected, re-discovering application url.","Url":"http://localhost/umbraco","SourceContext":"Umbraco.Core.Sync.ApplicationUrlHelper","ProcessId":24520,"ProcessName":"iisexpress","ThreadId":5,"AppDomainId":2,"AppDomainAppId":"LMW3SVC2ROOT","MachineName":"LAPTOP-FTNNAFT4","Log4NetLevel":"INFO ","HttpRequestNumber":3,"HttpRequestId":"5ea00126-cadb-42fc-92ae-53816560749a"}
{"@t":"2024-12-10T10:05:51.5470092Z","@mt":"ApplicationUrl: {UmbracoAppUrl} (UmbracoModule request)","UmbracoAppUrl":"http://localhost/umbraco","SourceContext":"Umbraco.Core.Sync.ApplicationUrlHelper","ProcessId":24520,"ProcessName":"iisexpress","ThreadId":6,"AppDomainId":2,"AppDomainAppId":"LMW3SVC2ROOT","MachineName":"LAPTOP-FTNNAFT4","Log4NetLevel":"INFO ","HttpRequestNumber":4,"HttpRequestId":"3de4b322-79cb-45d3-8c71-a12fd2a173f6"}
{"@t":"2024-12-10T10:05:51.5470092Z","@mt":"ApplicationUrl: {UmbracoAppUrl} (UmbracoModule request)","UmbracoAppUrl":"http://localhost/umbraco","SourceContext":"Umbraco.Core.Sync.ApplicationUrlHelper","ProcessId":24520,"ProcessName":"iisexpress","ThreadId":7,"AppDomainId":2,"AppDomainAppId":"LMW3SVC2ROOT","MachineName":"LAPTOP-FTNNAFT4","Log4NetLevel":"INFO ","HttpRequestNumber":2,"HttpRequestId":"a760773c-5489-44c7-b49d-a2ac9fada368"}
{"@t":"2024-12-10T10:05:51.5470092Z","@mt":"ApplicationUrl: {UmbracoAppUrl} (UmbracoModule request)","UmbracoAppUrl":"http://localhost/umbraco","SourceContext":"Umbraco.Core.Sync.ApplicationUrlHelper","ProcessId":24520,"ProcessName":"iisexpress","ThreadId":5,"AppDomainId":2,"AppDomainAppId":"LMW3SVC2ROOT","MachineName":"LAPTOP-FTNNAFT4","Log4NetLevel":"INFO ","HttpRequestNumber":3,"HttpRequestId":"5ea00126-cadb-42fc-92ae-53816560749a"}
{"@t":"2024-12-10T10:05:52.9529278Z","@mt":"Registered with MainDom, localContentDbExists? {LocalContentDbExists}, localMediaDbExists? {LocalMediaDbExists}","LocalContentDbExists":true,"LocalMediaDbExists":true,"SourceContext":"Umbraco.Web.PublishedCache.NuCache.PublishedSnapshotService","ProcessId":24520,"ProcessName":"iisexpress","ThreadId":7,"AppDomainId":2,"AppDomainAppId":"LMW3SVC2ROOT","MachineName":"LAPTOP-FTNNAFT4","Log4NetLevel":"INFO ","HttpRequestNumber":2,"HttpRequestId":"a760773c-5489-44c7-b49d-a2ac9fada368"}
{"@t":"2024-12-10T10:05:52.9539309Z","@mt":"Creating the content store, localContentDbExists? {LocalContentDbExists}","LocalContentDbExists":true,"SourceContext":"Umbraco.Web.PublishedCache.NuCache.PublishedSnapshotService","ProcessId":24520,"ProcessName":"iisexpress","ThreadId":7,"AppDomainId":2,"AppDomainAppId":"LMW3SVC2ROOT","MachineName":"LAPTOP-FTNNAFT4","Log4NetLevel":"INFO ","HttpRequestNumber":2,"HttpRequestId":"a760773c-5489-44c7-b49d-a2ac9fada368"}
{"@t":"2024-12-10T10:05:52.9574376Z","@mt":"Creating the media store, localMediaDbExists? {LocalMediaDbExists}","LocalMediaDbExists":true,"SourceContext":"Umbraco.Web.PublishedCache.NuCache.PublishedSnapshotService","ProcessId":24520,"ProcessName":"iisexpress","ThreadId":7,"AppDomainId":2,"AppDomainAppId":"LMW3SVC2ROOT","MachineName":"LAPTOP-FTNNAFT4","Log4NetLevel":"INFO ","HttpRequestNumber":2,"HttpRequestId":"a760773c-5489-44c7-b49d-a2ac9fada368"}
{"@t":"2024-12-10T10:05:54.7582022Z","@mt":"{StartMessage} [Timing {TimingId}]","StartMessage":"Loading content from local cache file","TimingId":"c7dccab","SourceContext":"Umbraco.Web.PublishedCache.NuCache.PublishedSnapshotService","ProcessId":24520,"ProcessName":"iisexpress","ThreadId":7,"AppDomainId":2,"AppDomainAppId":"LMW3SVC2ROOT","MachineName":"LAPTOP-FTNNAFT4","Log4NetLevel":"INFO ","HttpRequestNumber":2,"HttpRequestId":"a760773c-5489-44c7-b49d-a2ac9fada368"}
{"@t":"2024-12-10T10:05:54.8022182Z","@mt":"{EndMessage} ({Duration}ms) [Timing {TimingId}]","EndMessage":"Completed.","Duration":43,"TimingId":"c7dccab","SourceContext":"Umbraco.Web.PublishedCache.NuCache.PublishedSnapshotService","ProcessId":24520,"ProcessName":"iisexpress","ThreadId":7,"AppDomainId":2,"AppDomainAppId":"LMW3SVC2ROOT","MachineName":"LAPTOP-FTNNAFT4","Log4NetLevel":"INFO ","HttpRequestNumber":2,"HttpRequestId":"a760773c-5489-44c7-b49d-a2ac9fada368"}
{"@t":"2024-12-10T10:05:54.8170659Z","@mt":"{StartMessage} [Timing {TimingId}]","StartMessage":"Loading media from local cache file","TimingId":"1b69fc9","SourceContext":"Umbraco.Web.PublishedCache.NuCache.PublishedSnapshotService","ProcessId":24520,"ProcessName":"iisexpress","ThreadId":7,"AppDomainId":2,"AppDomainAppId":"LMW3SVC2ROOT","MachineName":"LAPTOP-FTNNAFT4","Log4NetLevel":"INFO ","HttpRequestNumber":2,"HttpRequestId":"a760773c-5489-44c7-b49d-a2ac9fada368"}
{"@t":"2024-12-10T10:05:54.8185457Z","@mt":"{EndMessage} ({Duration}ms) [Timing {TimingId}]","EndMessage":"Completed.","Duration":1,"TimingId":"1b69fc9","SourceContext":"Umbraco.Web.PublishedCache.NuCache.PublishedSnapshotService","ProcessId":24520,"ProcessName":"iisexpress","ThreadId":7,"AppDomainId":2,"AppDomainAppId":"LMW3SVC2ROOT","MachineName":"LAPTOP-FTNNAFT4","Log4NetLevel":"INFO ","HttpRequestNumber":2,"HttpRequestId":"a760773c-5489-44c7-b49d-a2ac9fada368"}
{"@t":"2024-12-10T10:05:55.0322356Z","@mt":"Forcing index {IndexerName} to be unlocked since it was left in a locked state","IndexerName":"InternalIndex","SourceContext":"Umbraco.Examine.ExamineExtensions","ProcessId":24520,"ProcessName":"iisexpress","ThreadId":7,"AppDomainId":2,"AppDomainAppId":"LMW3SVC2ROOT","MachineName":"LAPTOP-FTNNAFT4","Log4NetLevel":"INFO ","HttpRequestNumber":2,"HttpRequestId":"a760773c-5489-44c7-b49d-a2ac9fada368"}
{"@t":"2024-12-10T10:05:55.0352382Z","@mt":"Forcing index {IndexerName} to be unlocked since it was left in a locked state","IndexerName":"MembersIndex","SourceContext":"Umbraco.Examine.ExamineExtensions","ProcessId":24520,"ProcessName":"iisexpress","ThreadId":7,"AppDomainId":2,"AppDomainAppId":"LMW3SVC2ROOT","MachineName":"LAPTOP-FTNNAFT4","Log4NetLevel":"INFO ","HttpRequestNumber":2,"HttpRequestId":"a760773c-5489-44c7-b49d-a2ac9fada368"}
{"@t":"2024-12-10T10:05:55.0369989Z","@mt":"Forcing index {IndexerName} to be unlocked since it was left in a locked state","IndexerName":"ExternalIndex","SourceContext":"Umbraco.Examine.ExamineExtensions","ProcessId":24520,"ProcessName":"iisexpress","ThreadId":7,"AppDomainId":2,"AppDomainAppId":"LMW3SVC2ROOT","MachineName":"LAPTOP-FTNNAFT4","Log4NetLevel":"INFO ","HttpRequestNumber":2,"HttpRequestId":"a760773c-5489-44c7-b49d-a2ac9fada368"}
{"@t":"2024-12-10T10:05:55.0410428Z","@mt":"Starting initialize async background thread.","SourceContext":"Umbraco.Web.Search.BackgroundIndexRebuilder","ProcessId":24520,"ProcessName":"iisexpress","ThreadId":7,"AppDomainId":2,"AppDomainAppId":"LMW3SVC2ROOT","MachineName":"LAPTOP-FTNNAFT4","Log4NetLevel":"INFO ","HttpRequestNumber":2,"HttpRequestId":"a760773c-5489-44c7-b49d-a2ac9fada368"}
{"@t":"2024-12-10T10:08:59.9057128Z","@mt":"Scheduled health check results:","SourceContext":"Umbraco.Web.HealthCheck.HealthCheckResults","ProcessId":24520,"ProcessName":"iisexpress","ThreadId":11,"AppDomainId":2,"AppDomainAppId":"LMW3SVC2ROOT","MachineName":"LAPTOP-FTNNAFT4","Log4NetLevel":"INFO "}
{"@t":"2024-12-10T10:08:59.9057128Z","@mt":"Checks for '{HealthCheckName}' all completed successfully.","HealthCheckName":"Folder & File Permissions","SourceContext":"Umbraco.Web.HealthCheck.HealthCheckResults","ProcessId":24520,"ProcessName":"iisexpress","ThreadId":11,"AppDomainId":2,"AppDomainAppId":"LMW3SVC2ROOT","MachineName":"LAPTOP-FTNNAFT4","Log4NetLevel":"INFO "}
{"@t":"2024-12-10T10:08:59.9140446Z","@mt":"Result for {HealthCheckName}: {HealthCheckResult}, Message: '{HealthCheckMessage}'","HealthCheckName":"Folder & File Permissions","HealthCheckResult":"Success","HealthCheckMessage":"All folders have the correct permissions set.","SourceContext":"Umbraco.Web.HealthCheck.HealthCheckResults","ProcessId":24520,"ProcessName":"iisexpress","ThreadId":11,"AppDomainId":2,"AppDomainAppId":"LMW3SVC2ROOT","MachineName":"LAPTOP-FTNNAFT4","Log4NetLevel":"INFO "}
{"@t":"2024-12-10T10:08:59.9140446Z","@mt":"Result for {HealthCheckName}: {HealthCheckResult}, Message: '{HealthCheckMessage}'","HealthCheckName":"Folder & File Permissions","HealthCheckResult":"Success","HealthCheckMessage":"All files have the correct permissions set.","SourceContext":"Umbraco.Web.HealthCheck.HealthCheckResults","ProcessId":24520,"ProcessName":"iisexpress","ThreadId":11,"AppDomainId":2,"AppDomainAppId":"LMW3SVC2ROOT","MachineName":"LAPTOP-FTNNAFT4","Log4NetLevel":"INFO "}
{"@t":"2024-12-10T10:08:59.9160417Z","@mt":"Checks for '{HealthCheckName}' completed with errors.","@l":"Warning","HealthCheckName":"SMTP Settings","SourceContext":"Umbraco.Web.HealthCheck.HealthCheckResults","ProcessId":24520,"ProcessName":"iisexpress","ThreadId":11,"AppDomainId":2,"AppDomainAppId":"LMW3SVC2ROOT","MachineName":"LAPTOP-FTNNAFT4","Log4NetLevel":"WARN "}
{"@t":"2024-12-10T10:08:59.9160417Z","@mt":"Result for {HealthCheckName}: {HealthCheckResult}, Message: '{HealthCheckMessage}'","HealthCheckName":"SMTP Settings","HealthCheckResult":"Error","HealthCheckMessage":"In the Web.config file system.net/mailsettings section, the host is not configured.","SourceContext":"Umbraco.Web.HealthCheck.HealthCheckResults","ProcessId":24520,"ProcessName":"iisexpress","ThreadId":11,"AppDomainId":2,"AppDomainAppId":"LMW3SVC2ROOT","MachineName":"LAPTOP-FTNNAFT4","Log4NetLevel":"INFO "}
{"@t":"2024-12-10T10:08:59.9160417Z","@mt":"Checks for '{HealthCheckName}' completed with errors.","@l":"Warning","HealthCheckName":"Application URL Configuration","SourceContext":"Umbraco.Web.HealthCheck.HealthCheckResults","ProcessId":24520,"ProcessName":"iisexpress","ThreadId":11,"AppDomainId":2,"AppDomainAppId":"LMW3SVC2ROOT","MachineName":"LAPTOP-FTNNAFT4","Log4NetLevel":"WARN "}
{"@t":"2024-12-10T10:08:59.9160417Z","@mt":"Result for {HealthCheckName}: {HealthCheckResult}, Message: '{HealthCheckMessage}'","HealthCheckName":"Application URL Configuration","HealthCheckResult":"Warning","HealthCheckMessage":"The 'umbracoApplicationUrl' option is not set in your umbracoSettings.config file.","SourceContext":"Umbraco.Web.HealthCheck.HealthCheckResults","ProcessId":24520,"ProcessName":"iisexpress","ThreadId":11,"AppDomainId":2,"AppDomainAppId":"LMW3SVC2ROOT","MachineName":"LAPTOP-FTNNAFT4","Log4NetLevel":"INFO "}
{"@t":"2024-12-10T10:08:59.9160417Z","@mt":"Checks for '{HealthCheckName}' completed with errors.","@l":"Warning","HealthCheckName":"Cross-site scripting Protection (X-XSS-Protection header)","SourceContext":"Umbraco.Web.HealthCheck.HealthCheckResults","ProcessId":24520,"ProcessName":"iisexpress","ThreadId":11,"AppDomainId":2,"AppDomainAppId":"LMW3SVC2ROOT","MachineName":"LAPTOP-FTNNAFT4","Log4NetLevel":"WARN "}
{"@t":"2024-12-10T10:08:59.9160417Z","@mt":"Result for {HealthCheckName}: {HealthCheckResult}, Message: '{HealthCheckMessage}'","HealthCheckName":"Cross-site scripting Protection (X-XSS-Protection header)","HealthCheckResult":"Error","HealthCheckMessage":"The header <strong>X-XSS-Protection</strong> was not found.","SourceContext":"Umbraco.Web.HealthCheck.HealthCheckResults","ProcessId":24520,"ProcessName":"iisexpress","ThreadId":11,"AppDomainId":2,"AppDomainAppId":"LMW3SVC2ROOT","MachineName":"LAPTOP-FTNNAFT4","Log4NetLevel":"INFO "}
{"@t":"2024-12-10T10:08:59.9160417Z","@mt":"Checks for '{HealthCheckName}' completed with errors.","@l":"Warning","HealthCheckName":"Cookie hijacking and protocol downgrade attacks Protection (Strict-Transport-Security Header (HSTS))","SourceContext":"Umbraco.Web.HealthCheck.HealthCheckResults","ProcessId":24520,"ProcessName":"iisexpress","ThreadId":11,"AppDomainId":2,"AppDomainAppId":"LMW3SVC2ROOT","MachineName":"LAPTOP-FTNNAFT4","Log4NetLevel":"WARN "}
{"@t":"2024-12-10T10:08:59.9160417Z","@mt":"Result for {HealthCheckName}: {HealthCheckResult}, Message: '{HealthCheckMessage}'","HealthCheckName":"Cookie hijacking and protocol downgrade attacks Protection (Strict-Transport-Security Header (HSTS))","HealthCheckResult":"Error","HealthCheckMessage":"The header <strong>Strict-Transport-Security</strong> was not found.","SourceContext":"Umbraco.Web.HealthCheck.HealthCheckResults","ProcessId":24520,"ProcessName":"iisexpress","ThreadId":11,"AppDomainId":2,"AppDomainAppId":"LMW3SVC2ROOT","MachineName":"LAPTOP-FTNNAFT4","Log4NetLevel":"INFO "}
{"@t":"2024-12-10T10:08:59.9160417Z","@mt":"Checks for '{HealthCheckName}' completed with errors.","@l":"Warning","HealthCheckName":"Content/MIME Sniffing Protection","SourceContext":"Umbraco.Web.HealthCheck.HealthCheckResults","ProcessId":24520,"ProcessName":"iisexpress","ThreadId":11,"AppDomainId":2,"AppDomainAppId":"LMW3SVC2ROOT","MachineName":"LAPTOP-FTNNAFT4","Log4NetLevel":"WARN "}
{"@t":"2024-12-10T10:08:59.9160417Z","@mt":"Result for {HealthCheckName}: {HealthCheckResult}, Message: '{HealthCheckMessage}'","HealthCheckName":"Content/MIME Sniffing Protection","HealthCheckResult":"Error","HealthCheckMessage":"The header or meta-tag <strong>X-Content-Type-Options</strong> used to protect against MIME sniffing vulnerabilities was not found.","SourceContext":"Umbraco.Web.HealthCheck.HealthCheckResults","ProcessId":24520,"ProcessName":"iisexpress","ThreadId":11,"AppDomainId":2,"AppDomainAppId":"LMW3SVC2ROOT","MachineName":"LAPTOP-FTNNAFT4","Log4NetLevel":"INFO "}
{"@t":"2024-12-10T10:08:59.9160417Z","@mt":"Checks for '{HealthCheckName}' completed with errors.","@l":"Warning","HealthCheckName":"Excessive Headers","SourceContext":"Umbraco.Web.HealthCheck.HealthCheckResults","ProcessId":24520,"ProcessName":"iisexpress","ThreadId":11,"AppDomainId":2,"AppDomainAppId":"LMW3SVC2ROOT","MachineName":"LAPTOP-FTNNAFT4","Log4NetLevel":"WARN "}
{"@t":"2024-12-10T10:08:59.9160417Z","@mt":"Result for {HealthCheckName}: {HealthCheckResult}, Message: '{HealthCheckMessage}'","HealthCheckName":"Excessive Headers","HealthCheckResult":"Warning","HealthCheckMessage":"The following headers revealing information about the website technology were found: <strong>Server, X-Powered-By</strong>.","SourceContext":"Umbraco.Web.HealthCheck.HealthCheckResults","ProcessId":24520,"ProcessName":"iisexpress","ThreadId":11,"AppDomainId":2,"AppDomainAppId":"LMW3SVC2ROOT","MachineName":"LAPTOP-FTNNAFT4","Log4NetLevel":"INFO "}
{"@t":"2024-12-10T10:08:59.9160417Z","@mt":"Checks for '{HealthCheckName}' completed with errors.","@l":"Warning","HealthCheckName":"Click-Jacking Protection","SourceContext":"Umbraco.Web.HealthCheck.HealthCheckResults","ProcessId":24520,"ProcessName":"iisexpress","ThreadId":11,"AppDomainId":2,"AppDomainAppId":"LMW3SVC2ROOT","MachineName":"LAPTOP-FTNNAFT4","Log4NetLevel":"WARN "}
{"@t":"2024-12-10T10:08:59.9160417Z","@mt":"Result for {HealthCheckName}: {HealthCheckResult}, Message: '{HealthCheckMessage}'","HealthCheckName":"Click-Jacking Protection","HealthCheckResult":"Error","HealthCheckMessage":"The header or meta-tag <strong>X-Frame-Options</strong> used to control whether a site can be IFRAMEd by another was not found.","SourceContext":"Umbraco.Web.HealthCheck.HealthCheckResults","ProcessId":24520,"ProcessName":"iisexpress","ThreadId":11,"AppDomainId":2,"AppDomainAppId":"LMW3SVC2ROOT","MachineName":"LAPTOP-FTNNAFT4","Log4NetLevel":"INFO "}
{"@t":"2024-12-10T10:08:59.9160417Z","@mt":"Checks for '{HealthCheckName}' completed with errors.","@l":"Warning","HealthCheckName":"HTTPS Configuration","SourceContext":"Umbraco.Web.HealthCheck.HealthCheckResults","ProcessId":24520,"ProcessName":"iisexpress","ThreadId":11,"AppDomainId":2,"AppDomainAppId":"LMW3SVC2ROOT","MachineName":"LAPTOP-FTNNAFT4","Log4NetLevel":"WARN "}
{"@t":"2024-12-10T10:08:59.9160417Z","@mt":"Result for {HealthCheckName}: {HealthCheckResult}, Message: '{HealthCheckMessage}'","HealthCheckName":"HTTPS Configuration","HealthCheckResult":"Error","HealthCheckMessage":"You are currently not viewing the site using the HTTPS scheme.","SourceContext":"Umbraco.Web.HealthCheck.HealthCheckResults","ProcessId":24520,"ProcessName":"iisexpress","ThreadId":11,"AppDomainId":2,"AppDomainAppId":"LMW3SVC2ROOT","MachineName":"LAPTOP-FTNNAFT4","Log4NetLevel":"INFO "}
{"@t":"2024-12-10T10:08:59.9160417Z","@mt":"Result for {HealthCheckName}: {HealthCheckResult}, Message: '{HealthCheckMessage}'","HealthCheckName":"HTTPS Configuration","HealthCheckResult":"Info","HealthCheckMessage":"The appSetting 'Umbraco.Core.UseHttps' is set to 'false' in your web.config file. Once you access this site using the HTTPS scheme, that should be set to 'true'.","SourceContext":"Umbraco.Web.HealthCheck.HealthCheckResults","ProcessId":24520,"ProcessName":"iisexpress","ThreadId":11,"AppDomainId":2,"AppDomainAppId":"LMW3SVC2ROOT","MachineName":"LAPTOP-FTNNAFT4","Log4NetLevel":"INFO "}
{"@t":"2024-12-10T10:08:59.9160417Z","@mt":"Result for {HealthCheckName}: {HealthCheckResult}, Message: '{HealthCheckMessage}'","HealthCheckName":"HTTPS Configuration","HealthCheckResult":"Error","HealthCheckMessage":"Error pinging the URL https://localhost/umbraco - 'Unable to connect to the remote server'","SourceContext":"Umbraco.Web.HealthCheck.HealthCheckResults","ProcessId":24520,"ProcessName":"iisexpress","ThreadId":11,"AppDomainId":2,"AppDomainAppId":"LMW3SVC2ROOT","MachineName":"LAPTOP-FTNNAFT4","Log4NetLevel":"INFO "}
{"@t":"2024-12-10T10:08:59.9160417Z","@mt":"Checks for '{HealthCheckName}' all completed successfully.","HealthCheckName":"Database data integrity check","SourceContext":"Umbraco.Web.HealthCheck.HealthCheckResults","ProcessId":24520,"ProcessName":"iisexpress","ThreadId":11,"AppDomainId":2,"AppDomainAppId":"LMW3SVC2ROOT","MachineName":"LAPTOP-FTNNAFT4","Log4NetLevel":"INFO "}
{"@t":"2024-12-10T10:08:59.9160417Z","@mt":"Result for {HealthCheckName}: {HealthCheckResult}, Message: '{HealthCheckMessage}'","HealthCheckName":"Database data integrity check","HealthCheckResult":"Success","HealthCheckMessage":"<p>All document paths are valid</p>\r\n","SourceContext":"Umbraco.Web.HealthCheck.HealthCheckResults","ProcessId":24520,"ProcessName":"iisexpress","ThreadId":11,"AppDomainId":2,"AppDomainAppId":"LMW3SVC2ROOT","MachineName":"LAPTOP-FTNNAFT4","Log4NetLevel":"INFO "}
{"@t":"2024-12-10T10:08:59.9160417Z","@mt":"Result for {HealthCheckName}: {HealthCheckResult}, Message: '{HealthCheckMessage}'","HealthCheckName":"Database data integrity check","HealthCheckResult":"Success","HealthCheckMessage":"<p>All media paths are valid</p>\r\n","SourceContext":"Umbraco.Web.HealthCheck.HealthCheckResults","ProcessId":24520,"ProcessName":"iisexpress","ThreadId":11,"AppDomainId":2,"AppDomainAppId":"LMW3SVC2ROOT","MachineName":"LAPTOP-FTNNAFT4","Log4NetLevel":"INFO "}
{"@t":"2024-12-10T10:08:59.9160417Z","@mt":"Checks for '{HealthCheckName}' completed with errors.","@l":"Warning","HealthCheckName":"Macro errors","SourceContext":"Umbraco.Web.HealthCheck.HealthCheckResults","ProcessId":24520,"ProcessName":"iisexpress","ThreadId":11,"AppDomainId":2,"AppDomainAppId":"LMW3SVC2ROOT","MachineName":"LAPTOP-FTNNAFT4","Log4NetLevel":"WARN "}
{"@t":"2024-12-10T10:08:59.9160417Z","@mt":"Result for {HealthCheckName}: {HealthCheckResult}, Message: '{HealthCheckMessage}'","HealthCheckName":"Macro errors","HealthCheckResult":"Error","HealthCheckMessage":"MacroErrors are set to 'throw' which will prevent some or all pages in your site from loading completely if there are any errors in macros. Rectifying this will set the value to 'inline'.","SourceContext":"Umbraco.Web.HealthCheck.HealthCheckResults","ProcessId":24520,"ProcessName":"iisexpress","ThreadId":11,"AppDomainId":2,"AppDomainAppId":"LMW3SVC2ROOT","MachineName":"LAPTOP-FTNNAFT4","Log4NetLevel":"INFO "}
{"@t":"2024-12-10T10:08:59.9160417Z","@mt":"Checks for '{HealthCheckName}' completed with errors.","@l":"Warning","HealthCheckName":"Notification Email Settings","SourceContext":"Umbraco.Web.HealthCheck.HealthCheckResults","ProcessId":24520,"ProcessName":"iisexpress","ThreadId":11,"AppDomainId":2,"AppDomainAppId":"LMW3SVC2ROOT","MachineName":"LAPTOP-FTNNAFT4","Log4NetLevel":"WARN "}
{"@t":"2024-12-10T10:08:59.9160417Z","@mt":"Result for {HealthCheckName}: {HealthCheckResult}, Message: '{HealthCheckMessage}'","HealthCheckName":"Notification Email Settings","HealthCheckResult":"Error","HealthCheckMessage":"Notification email is still set to the default value of <strong>your@email.here</strong>.","SourceContext":"Umbraco.Web.HealthCheck.HealthCheckResults","ProcessId":24520,"ProcessName":"iisexpress","ThreadId":11,"AppDomainId":2,"AppDomainAppId":"LMW3SVC2ROOT","MachineName":"LAPTOP-FTNNAFT4","Log4NetLevel":"INFO "}
{"@t":"2024-12-10T10:08:59.9160417Z","@mt":"Checks for '{HealthCheckName}' all completed successfully.","HealthCheckName":"Try Skip IIS Custom Errors","SourceContext":"Umbraco.Web.HealthCheck.HealthCheckResults","ProcessId":24520,"ProcessName":"iisexpress","ThreadId":11,"AppDomainId":2,"AppDomainAppId":"LMW3SVC2ROOT","MachineName":"LAPTOP-FTNNAFT4","Log4NetLevel":"INFO "}
{"@t":"2024-12-10T10:08:59.9160417Z","@mt":"Result for {HealthCheckName}: {HealthCheckResult}, Message: '{HealthCheckMessage}'","HealthCheckName":"Try Skip IIS Custom Errors","HealthCheckResult":"Success","HealthCheckMessage":"Try Skip IIS Custom Errors is set to 'true' and you're using IIS version '10.0'.","SourceContext":"Umbraco.Web.HealthCheck.HealthCheckResults","ProcessId":24520,"ProcessName":"iisexpress","ThreadId":11,"AppDomainId":2,"AppDomainAppId":"LMW3SVC2ROOT","MachineName":"LAPTOP-FTNNAFT4","Log4NetLevel":"INFO "}
{"@t":"2024-12-10T10:08:59.9160417Z","@mt":"Checks for '{HealthCheckName}' all completed successfully.","HealthCheckName":"Custom Errors","SourceContext":"Umbraco.Web.HealthCheck.HealthCheckResults","ProcessId":24520,"ProcessName":"iisexpress","ThreadId":11,"AppDomainId":2,"AppDomainAppId":"LMW3SVC2ROOT","MachineName":"LAPTOP-FTNNAFT4","Log4NetLevel":"INFO "}
{"@t":"2024-12-10T10:08:59.9160417Z","@mt":"Result for {HealthCheckName}: {HealthCheckResult}, Message: '{HealthCheckMessage}'","HealthCheckName":"Custom Errors","HealthCheckResult":"Success","HealthCheckMessage":"Custom errors are set to 'RemoteOnly'.","SourceContext":"Umbraco.Web.HealthCheck.HealthCheckResults","ProcessId":24520,"ProcessName":"iisexpress","ThreadId":11,"AppDomainId":2,"AppDomainAppId":"LMW3SVC2ROOT","MachineName":"LAPTOP-FTNNAFT4","Log4NetLevel":"INFO "}
{"@t":"2024-12-10T10:08:59.9160417Z","@mt":"Checks for '{HealthCheckName}' all completed successfully.","HealthCheckName":"Trace Mode","SourceContext":"Umbraco.Web.HealthCheck.HealthCheckResults","ProcessId":24520,"ProcessName":"iisexpress","ThreadId":11,"AppDomainId":2,"AppDomainAppId":"LMW3SVC2ROOT","MachineName":"LAPTOP-FTNNAFT4","Log4NetLevel":"INFO "}
{"@t":"2024-12-10T10:08:59.9160417Z","@mt":"Result for {HealthCheckName}: {HealthCheckResult}, Message: '{HealthCheckMessage}'","HealthCheckName":"Trace Mode","HealthCheckResult":"Success","HealthCheckMessage":"Trace mode is disabled.","SourceContext":"Umbraco.Web.HealthCheck.HealthCheckResults","ProcessId":24520,"ProcessName":"iisexpress","ThreadId":11,"AppDomainId":2,"AppDomainAppId":"LMW3SVC2ROOT","MachineName":"LAPTOP-FTNNAFT4","Log4NetLevel":"INFO "}
{"@t":"2024-12-10T10:08:59.9160417Z","@mt":"Checks for '{HealthCheckName}' completed with errors.","@l":"Warning","HealthCheckName":"Debug Compilation Mode","SourceContext":"Umbraco.Web.HealthCheck.HealthCheckResults","ProcessId":24520,"ProcessName":"iisexpress","ThreadId":11,"AppDomainId":2,"AppDomainAppId":"LMW3SVC2ROOT","MachineName":"LAPTOP-FTNNAFT4","Log4NetLevel":"WARN "}
{"@t":"2024-12-10T10:08:59.9160417Z","@mt":"Result for {HealthCheckName}: {HealthCheckResult}, Message: '{HealthCheckMessage}'","HealthCheckName":"Debug Compilation Mode","HealthCheckResult":"Error","HealthCheckMessage":"Debug compilation mode is currently enabled. It is recommended to disable this setting before go live.","SourceContext":"Umbraco.Web.HealthCheck.HealthCheckResults","ProcessId":24520,"ProcessName":"iisexpress","ThreadId":11,"AppDomainId":2,"AppDomainAppId":"LMW3SVC2ROOT","MachineName":"LAPTOP-FTNNAFT4","Log4NetLevel":"INFO "}
